ezjsonpy/__init__.py
ezjsonpy/config_loader.py
ezjsonpy/exceptions.py
ezjsonpy/lang_loader.py
ezjsonpy-1.0.5.dist-info/METADATA
ezjsonpy-1.0.5.dist-info/WHEEL
ezjsonpy-1.0.5.dist-info/top_level.txt
ezjsonpy-1.0.5.dist-info/RECORD
