Metadata-Version: 2.1
Name: ezjsonpy
Version: 1.0.5
Summary: Python library that allows you to easily load languages and settings ​​into your project using JSON files
Author-email: "Pedro Agustin Vega (wrrulos)" <pedroagustinvega04@gmail.com>
License: MIT License
Project-URL: homepage, https://github.com/pedroagustinvega/ezjsonpy
Project-URL: documentation, https://github.com/pedroagustinvega/ezjsonpy
Project-URL: repository, https://github.com/pedroagustinvega/ezjsonpy
Keywords: language,settings,python,json
Classifier: Programming Language :: Python :: 3
Classifier: License :: OSI Approved :: MIT License
Classifier: Operating System :: OS Independent
Requires-Python: >=3.6
Requires-Dist: aiofiles
